VMConnect/__init__.py
VMConnect/cache.py
VMConnect/core.py
VMConnect/exceptions.py
VMConnect-1.1.7.data/scripts/VMConnect-cli
VMConnect-1.1.7.dist-info/LICENSE
VMConnect-1.1.7.dist-info/METADATA
VMConnect-1.1.7.dist-info/WHEEL
VMConnect-1.1.7.dist-info/top_level.txt
VMConnect-1.1.7.dist-info/RECORD
