Metadata-Version: 2.1
Name: VMConnect
Version: 1.1.7
Summary: VMware vSphere Connector Module for Python
Home-page: https://github.com/hushki502/VMConnect
Download-URL: https://github.com/hushki502/VMConnect/releases
Author: Hushki Manager
Author-email: hushki502@gmail.com
License: BSD
License-File: LICENSE
Requires-Dist: pyvmomi (>=6.7.3)
Requires-Dist: docopt (>=0.6.2)
Requires-Dist: tabulate (>=0.8.3)
